tak_agent/__init__.py
tak_agent/__main__.py
tak_agent/cli.py
tak_agent/run.py
tak_agent/core/__init__.py
tak_agent/core/agent.py
tak_agent/core/config.py
tak_agent/core/cot_builder.py
tak_agent/core/tak_client.py
tak_agent/llm/__init__.py
tak_agent/llm/base_provider.py
tak_agent/llm/claude_provider.py
tak_agent/llm/groq_provider.py
tak_agent/plugins/__init__.py
tak_agent/utils/__init__.py
tak_agent/utils/geo.py
tak_ai_agent-1.0.0.dist-info/licenses/LICENSE
tak_ai_agent-1.0.0.dist-info/METADATA
tak_ai_agent-1.0.0.dist-info/WHEEL
tak_ai_agent-1.0.0.dist-info/entry_points.txt
tak_ai_agent-1.0.0.dist-info/top_level.txt
tak_ai_agent-1.0.0.dist-info/RECORD
