Metadata-Version: 2.4
Name: tak-ai-agent
Version: 1.0.0
Summary: AI agent framework for TAK (Team Awareness Kit) networks
Home-page: https://github.com/overwatch-tak/tak-ai-agent
Author: OVERWATCH
Author-email: overwatch@grg-tak.com
License: MIT
Project-URL: Documentation, https://github.com/overwatch-tak/tak-ai-agent#readme
Project-URL: Source, https://github.com/overwatch-tak/tak-ai-agent
Project-URL: Issue Tracker, https://github.com/overwatch-tak/tak-ai-agent/issues
Keywords: tak,atak,wintak,cot,cursor-on-target,situational-awareness,ai-agent,llm,tactical,geospatial
Classifier: Development Status :: 4 - Beta
Classifier: Intended Audience :: Developers
Classifier: Intended Audience :: Science/Research
Classifier: License :: OSI Approved :: MIT License
Classifier: Operating System :: OS Independent
Classifier: Programming Language :: Python :: 3
Classifier: Programming Language :: Python :: 3.11
Classifier: Programming Language :: Python :: 3.12
Classifier: Topic :: Communications
Classifier: Topic :: Scientific/Engineering :: GIS
Classifier: Topic :: Scientific/Engineering :: Artificial Intelligence
Classifier: Framework :: AsyncIO
Requires-Python: >=3.11
License-File: LICENSE
Requires-Dist: pytak>=6.2.0
Requires-Dist: aiohttp>=3.9.0
Requires-Dist: anthropic>=0.40.0
Requires-Dist: groq>=0.4.0
Requires-Dist: pyyaml>=6.0
Requires-Dist: python-dotenv>=1.0.0
Requires-Dist: geopy>=2.4.0
Requires-Dist: cryptography>=41.0.0
Requires-Dist: xmltodict>=0.13.0
Provides-Extra: dev
Requires-Dist: pytest>=7.0.0; extra == "dev"
Requires-Dist: pytest-asyncio>=0.21.0; extra == "dev"
Requires-Dist: black>=23.0.0; extra == "dev"
Requires-Dist: ruff>=0.1.0; extra == "dev"
Dynamic: author
Dynamic: author-email
Dynamic: classifier
Dynamic: description
Dynamic: description-content-type
Dynamic: home-page
Dynamic: keywords
Dynamic: license
Dynamic: license-file
Dynamic: project-url
Dynamic: provides-extra
Dynamic: requires-dist
Dynamic: requires-python
Dynamic: summary
